vaccinewatcher/__init__.py
vaccinewatcher/logger.py
vaccinewatcher/watcher.py
vaccinewatcher-0.0.1.dist-info/LICENSE
vaccinewatcher-0.0.1.dist-info/METADATA
vaccinewatcher-0.0.1.dist-info/WHEEL
vaccinewatcher-0.0.1.dist-info/entry_points.txt
vaccinewatcher-0.0.1.dist-info/top_level.txt
vaccinewatcher-0.0.1.dist-info/RECORD
