Metadata-Version: 2.1
Name: vaccinewatcher
Version: 0.0.1
Summary: Monitor Vaccine Availability from your Local CVS and Walgreens (US Only).
Home-page: http://github.com/trisongz/vaccinewatcher
Author: Tri Songz
Author-email: ts@scontentengine.ai
License: UNKNOWN
Platform: UNKNOWN
Classifier: Development Status :: 3 - Alpha
Classifier: Environment :: Console
Classifier: Intended Audience :: Developers
Requires-Python: >3.6
Requires-Dist: selenium
Requires-Dist: selenium-wire
Requires-Dist: undetected-chromedriver
Requires-Dist: elemental
